NicePy/Adherence.py
NicePy/Agents.py
NicePy/Config.py
NicePy/Connection.py
NicePy/Contacts.py
NicePy/Dispositions.py
NicePy/Funcs.py
NicePy/NicePy.py
NicePy/__init__.py
NicePy-1.0.0.dist-info/METADATA
NicePy-1.0.0.dist-info/WHEEL
NicePy-1.0.0.dist-info/license.txt
NicePy-1.0.0.dist-info/top_level.txt
NicePy-1.0.0.dist-info/RECORD
