Metadata-Version: 2.1
Name: NicePy
Version: 1.0.0
Summary: An API library for NICE CXOne
Author: Jim Weiler
Author-email: Jim Weiler <jim@vaelek.com>
Maintainer-email: Jim Weiler <jim@vaelek.com>
License: MIT License
Project-URL: Homepage, https://github.com/Vaelek/NicePy
Project-URL: Bug Reports, https://github.com/Vaelek/NicePy/issues
Project-URL: Source, https://github.com/Vaelek/NicePy
Keywords: CXOne,inContact,NICE
Classifier: Development Status :: 4 - Beta
Classifier: License :: OSI Approved :: MIT License
Classifier: Programming Language :: Python :: 3.8
Requires-Python: >=3.8
License-File: license.txt
Requires-Dist: requests
Requires-Dist: requests-oauthlib
Requires-Dist: oauthlib
Requires-Dist: python-dateutil
Requires-Dist: pydub
Requires-Dist: joblib
Requires-Dist: tzlocal
Requires-Dist: debugpy
